btoa/__init__.py
btoa/main.py
btoa-1.0.1.dist-info/METADATA
btoa-1.0.1.dist-info/WHEEL
btoa-1.0.1.dist-info/top_level.txt
btoa-1.0.1.dist-info/RECORD
