Metadata-Version: 2.1
Name: btoa
Version: 1.0.1
Summary: Python implementation btoa and atob functions from javascript
Author-email: LazyDeus <dimaprodeus@yandex.ru>
Project-URL: Homepage, https://github.com/Demetrous-fd/btoa
Project-URL: Bug Tracker, https://github.com/Demetrous-fd/btoa/issues
Classifier: Programming Language :: Python :: 3
Classifier: License :: OSI Approved :: MIT License
Classifier: Operating System :: OS Independent
Requires-Python: >=3.6
